demo.py
noja_reader-1.0.0.dist-info/licenses/LICENSE
reader/__init__.py
reader/__main__.py
reader/config.toml
reader/feed.py
reader/viewer.py
noja_reader-1.0.0.dist-info/METADATA
noja_reader-1.0.0.dist-info/WHEEL
noja_reader-1.0.0.dist-info/entry_points.txt
noja_reader-1.0.0.dist-info/top_level.txt
noja_reader-1.0.0.dist-info/RECORD
